DependencyLibrary.py
robotframework_dependencylibrary-4.0.1.dist-info/LICENSE
robotframework_dependencylibrary-4.0.1.dist-info/METADATA
robotframework_dependencylibrary-4.0.1.dist-info/WHEEL
robotframework_dependencylibrary-4.0.1.dist-info/top_level.txt
robotframework_dependencylibrary-4.0.1.dist-info/RECORD
