Metadata-Version: 2.1
Name: robotframework-dependencylibrary
Version: 4.0.1
Summary: Declare dependencies between Robot Framework tests
Home-page: https://github.com/mentalisttraceur/robotframework-dependencylibrary
Author: Alexander Kozhevnikov
Author-email: mentalisttraceur@gmail.com
License: 0BSD (BSD Zero Clause License)
Classifier: Development Status :: 5 - Production/Stable
Classifier: Framework :: Robot Framework :: Library
Classifier: Topic :: Software Development :: Testing
Classifier: Programming Language :: Python :: 3
Classifier: Programming Language :: Python :: 2
Classifier: Operating System :: OS Independent
License-File: LICENSE
Requires-Dist: robotframework
